{
  "code": 0,
  "msg": "success",
  "data": {
    "quoteReviewInfo": {
      "reviewId": "849256195201761280",
      "cbid": "25583693309808304",
      "ccid": "69203747871449297",
      "guid": "2136173392",
      "userId": "354168061",
      "nickName": "桂曦月",
      "avatar": "https://qidian.qpic.cn/qd_face/349573/9133387/100",
      "segmentId": 5,
      "content": "上班没人敢和你争辩",
      "status": 1,
      "createTime": "2023-03-04 12:37:11",
      "createTimestamp": 1677904631,
      "updateTime": "2024-11-21 11:19:01",
      "quoteReviewId": "0",
      "quoteContent": "",
      "quoteGuid": "0",
      "quoteUserId": "0",
      "quoteNickName": "",
      "type": 2,
      "likeCount": 10193,
      "dislikeCount": 0,
      "userLike": false,
      "userDislike": false,
      "isSelf": false,
      "essenceStatus": false,
      "riseStatus": false,
      "level": 130,
      "imagePre": "",
      "imageDetail": "",
      "rootReviewId": "849256195201761280",
      "rootReviewReplyCount": 53,
      "ipAddress": ""
    },
    "list": [
      {
        "reviewId": "1001134669020594176",
        "cbid": "25583693309808304",
        "ccid": "69203747871449297",
        "guid": "120002238661",
        "userId": "302040769",
        "nickName": "悲歌醉红尘1985",
        "avatar": "https://qidian.qpic.cn/qd_face/349573/219/100",
        "segmentId": 5,
        "content": "有人争辩就不敢上班了",
        "status": 1,
        "createTime": "04-26 15:08:01",
        "createTimestamp": 1714115281,
        "updateTime": "2024-07-05 21:58:34",
        "quoteReviewId": "849256195201761280",
        "quoteContent": "",
        "quoteGuid": "2136173392",
        "quoteUserId": "354168061",
        "quoteNickName": "桂曦月",
        "type": 10,
        "likeCount": 3,
        "dislikeCount": 0,
        "userLike": false,
        "userDislike": false,
        "isSelf": false,
        "essenceStatus": false,
        "riseStatus": false,
        "level": 926,
        "imagePre": "",
        "imageDetail": "",
        "rootReviewId": "849256195201761280",
        "rootReviewReplyCount": 0,
        "ipAddress": "安徽"
      },
      {
        "reviewId": "912741940046135296",
        "cbid": "25583693309808304",
        "ccid": "69203747871449297",
        "guid": "2390719668",
        "userId": "403691638",
        "nickName": "Steam",
        "avatar": "https://qidian.qpic.cn/qd_face/349573/10467347/100",
        "segmentId": 5,
        "content": "但是其实可以和他们打牌的，你说是吧，马里奇。",
        "status": 1,
        "createTime": "2023-08-26 17:06:52",
        "createTimestamp": 1693040812,
        "updateTime": "2024-07-05 21:58:34",
        "quoteReviewId": "849256195201761280",
        "quoteContent": "",
        "quoteGuid": "2136173392",
        "quoteUserId": "354168061",
        "quoteNickName": "桂曦月",
        "type": 10,
        "likeCount": 2,
        "dislikeCount": 0,
        "userLike": false,
        "userDislike": false,
        "isSelf": false,
        "essenceStatus": false,
        "riseStatus": false,
        "level": 897,
        "imagePre": "",
        "imageDetail": "",
        "rootReviewId": "849256195201761280",
        "rootReviewReplyCount": 0,
        "ipAddress": "广东"
      },
      {
        "reviewId": "904317006877949952",
        "cbid": "25583693309808304",
        "ccid": "69203747871449297",
        "guid": "854033270525",
        "userId": "368248443",
        "nickName": "Hooya丶294",
        "avatar": "https://qidian.qpic.cn/qd_face/349573/12063106/100",
        "segmentId": 5,
        "content": "6",
        "status": 1,
        "createTime": "2023-08-03 11:09:12",
        "createTimestamp": 1691032152,
        "updateTime": "2024-07-05 21:58:34",
        "quoteReviewId": "849256195201761280",
        "quoteContent": "",
        "quoteGuid": "2136173392",
        "quoteUserId": "354168061",
        "quoteNickName": "桂曦月",
        "type": 10,
        "likeCount": 0,
        "dislikeCount": 0,
        "userLike": false,
        "userDislike": false,
        "isSelf": false,
        "essenceStatus": false,
        "riseStatus": false,
        "level": 892,
        "imagePre": "",
        "imageDetail": "",
        "rootReviewId": "849256195201761280",
        "rootReviewReplyCount": 0,
        "ipAddress": "浙江"
      },
      {
        "reviewId": "893080534803873792",
        "cbid": "25583693309808304",
        "ccid": "69203747871449297",
        "guid": "800146427503",
        "userId": "146427503",
        "nickName": "左眼清明",
        "avatar": "https://qidian.qpic.cn/qd_face/349573/8433987/100",
        "segmentId": 5,
        "content": "不服的都给我站起来[fn=4]",
        "status": 1,
        "createTime": "2023-07-03 10:59:28",
        "createTimestamp": 1688353168,
        "updateTime": "2024-07-05 21:58:34",
        "quoteReviewId": "849256195201761280",
        "quoteContent": "",
        "quoteGuid": "2136173392",
        "quoteUserId": "354168061",
        "quoteNickName": "桂曦月",
        "type": 10,
        "likeCount": 6,
        "dislikeCount": 0,
        "userLike": false,
        "userDislike": false,
        "isSelf": false,
        "essenceStatus": false,
        "riseStatus": false,
        "level": 886,
        "imagePre": "",
        "imageDetail": "",
        "rootReviewId": "849256195201761280",
        "rootReviewReplyCount": 0,
        "ipAddress": "吉林"
      },
      {
        "reviewId": "880555873964654592",
        "cbid": "25583693309808304",
        "ccid": "69203747871449297",
        "guid": "120191957622",
        "userId": "363095397",
        "nickName": "蟒子美味又营养",
        "avatar": "https://qidian.qpic.cn/qd_face/349573/8556522/100",
        "segmentId": 5,
        "content": "不怕和你争辩，就怕他们辩赢了——某不愿透露姓名的囚徒序列强者",
        "status": 1,
        "createTime": "2023-05-29 21:30:56",
        "createTimestamp": 1685367056,
        "updateTime": "2024-07-05 21:58:34",
        "quoteReviewId": "849256195201761280",
        "quoteContent": "",
        "quoteGuid": "2136173392",
        "quoteUserId": "354168061",
        "quoteNickName": "桂曦月",
        "type": 10,
        "likeCount": 7,
        "dislikeCount": 0,
        "userLike": false,
        "userDislike": false,
        "isSelf": false,
        "essenceStatus": false,
        "riseStatus": false,
        "level": 867,
        "imagePre": "",
        "imageDetail": "",
        "rootReviewId": "849256195201761280",
        "rootReviewReplyCount": 0,
        "ipAddress": "辽宁"
      },
      {
        "reviewId": "865227415403429888",
        "cbid": "25583693309808304",
        "ccid": "69203747871449297",
        "guid": "3235639520",
        "userId": "313465309",
        "nickName": "WD江总",
        "avatar": "https://qidian.qpic.cn/qd_face/349573/12441198/100",
        "segmentId": 5,
        "content": "难说哦",
        "status": 1,
        "createTime": "2023-04-17 14:21:07",
        "createTimestamp": 1681712467,
        "updateTime": "2024-07-05 21:58:34",
        "quoteReviewId": "849256195201761280",
        "quoteContent": "",
        "quoteGuid": "2136173392",
        "quoteUserId": "354168061",
        "quoteNickName": "桂曦月",
        "type": 10,
        "likeCount": 1,
        "dislikeCount": 0,
        "userLike": false,
        "userDislike": false,
        "isSelf": false,
        "essenceStatus": false,
        "riseStatus": false,
        "level": 819,
        "imagePre": "",
        "imageDetail": "",
        "rootReviewId": "849256195201761280",
        "rootReviewReplyCount": 0,
        "ipAddress": "河南"
      },
      {
        "reviewId": "863860561732763648",
        "cbid": "25583693309808304",
        "ccid": "69203747871449297",
        "guid": "2136173392",
        "userId": "354168061",
        "nickName": "桂曦月",
        "avatar": "https://qidian.qpic.cn/qd_face/349573/9133387/100",
        "segmentId": 5,
        "content": "错误的，能和他争辩的都不是人（）",
        "status": 1,
        "createTime": "2023-04-13 19:49:43",
        "createTimestamp": 1681386583,
        "updateTime": "2024-07-05 21:58:34",
        "quoteReviewId": "862993650262212608",
        "quoteContent": "",
        "quoteGuid": "734437205",
        "quoteUserId": "303357231",
        "quoteNickName": "Theone铭",
        "type": 10,
        "likeCount": 0,
        "dislikeCount": 0,
        "userLike": false,
        "userDislike": false,
        "isSelf": false,
        "essenceStatus": false,
        "riseStatus": false,
        "level": 815,
        "imagePre": "",
        "imageDetail": "",
        "rootReviewId": "849256195201761280",
        "rootReviewReplyCount": 0,
        "ipAddress": "广东"
      },
      {
        "reviewId": "862993650262212608",
        "cbid": "25583693309808304",
        "ccid": "69203747871449297",
        "guid": "734437205",
        "userId": "303357231",
        "nickName": "Theone铭",
        "avatar": "https://qidian.qpic.cn/qd_face/349573/224/100",
        "segmentId": 5,
        "content": "这话可不敢乱说，立flag是要被制裁的",
        "status": 1,
        "createTime": "2023-04-11 10:24:56",
        "createTimestamp": 1681179896,
        "updateTime": "2024-07-05 21:58:34",
        "quoteReviewId": "849256195201761280",
        "quoteContent": "",
        "quoteGuid": "2136173392",
        "quoteUserId": "354168061",
        "quoteNickName": "桂曦月",
        "type": 10,
        "likeCount": 0,
        "dislikeCount": 0,
        "userLike": false,
        "userDislike": false,
        "isSelf": false,
        "essenceStatus": false,
        "riseStatus": false,
        "level": 813,
        "imagePre": "",
        "imageDetail": "",
        "rootReviewId": "849256195201761280",
        "rootReviewReplyCount": 0,
        "ipAddress": "重庆"
      },
      {
        "reviewId": "862788623149170688",
        "cbid": "25583693309808304",
        "ccid": "69203747871449297",
        "guid": "3097126926",
        "userId": "370128421",
        "nickName": "无语望天",
        "avatar": "https://qidian.gtimg.com/qd/images/ico/default_user.0.2.png",
        "segmentId": 5,
        "content": "最后输了，马里奇那段笑死了哈哈哈",
        "status": 1,
        "createTime": "2023-04-10 20:50:13",
        "createTimestamp": 1681131013,
        "updateTime": "2024-07-05 21:58:34",
        "quoteReviewId": "849276314963476480",
        "quoteContent": "",
        "quoteGuid": "854063165174",
        "quoteUserId": "406869520",
        "quoteNickName": "书友20230126175325999",
        "type": 10,
        "likeCount": 1,
        "dislikeCount": 0,
        "userLike": false,
        "userDislike": false,
        "isSelf": false,
        "essenceStatus": false,
        "riseStatus": false,
        "level": 810,
        "imagePre": "",
        "imageDetail": "",
        "rootReviewId": "849256195201761280",
        "rootReviewReplyCount": 0,
        "ipAddress": "广东"
      },
      {
        "reviewId": "861673196402507776",
        "cbid": "25583693309808304",
        "ccid": "69203747871449297",
        "guid": "854049645636",
        "userId": "389445502",
        "nickName": "可燃乌龍茶",
        "avatar": "https://qidian.qpic.cn/qd_face/349573/10860756/100",
        "segmentId": 5,
        "content": "哈哈哈哈还敢顶嘴？",
        "status": 1,
        "createTime": "2023-04-07 18:57:55",
        "createTimestamp": 1680865075,
        "updateTime": "2024-07-05 21:58:34",
        "quoteReviewId": "849256195201761280",
        "quoteContent": "",
        "quoteGuid": "2136173392",
        "quoteUserId": "354168061",
        "quoteNickName": "桂曦月",
        "type": 10,
        "likeCount": 3,
        "dislikeCount": 0,
        "userLike": false,
        "userDislike": false,
        "isSelf": false,
        "essenceStatus": false,
        "riseStatus": false,
        "level": 808,
        "imagePre": "",
        "imageDetail": "",
        "rootReviewId": "849256195201761280",
        "rootReviewReplyCount": 0,
        "ipAddress": "广东"
      },
      {
        "reviewId": "860567215266463744",
        "cbid": "25583693309808304",
        "ccid": "69203747871449297",
        "guid": "2136173392",
        "userId": "354168061",
        "nickName": "桂曦月",
        "avatar": "https://qidian.qpic.cn/qd_face/349573/9133387/100",
        "segmentId": 5,
        "content": "争辩的都不是人捏（）",
        "status": 1,
        "createTime": "2023-04-04 17:43:08",
        "createTimestamp": 1680601388,
        "updateTime": "2024-07-05 21:58:34",
        "quoteReviewId": "849256195201761280",
        "quoteContent": "",
        "quoteGuid": "2136173392",
        "quoteUserId": "354168061",
        "quoteNickName": "桂曦月",
        "type": 10,
        "likeCount": 1,
        "dislikeCount": 0,
        "userLike": false,
        "userDislike": false,
        "isSelf": false,
        "essenceStatus": false,
        "riseStatus": false,
        "level": 805,
        "imagePre": "",
        "imageDetail": "",
        "rootReviewId": "849256195201761280",
        "rootReviewReplyCount": 0,
        "ipAddress": "广东"
      },
      {
        "reviewId": "859938290836307968",
        "cbid": "25583693309808304",
        "ccid": "69203747871449297",
        "guid": "129612751295",
        "userId": "340623842",
        "nickName": "云天游yty",
        "avatar": "https://qidian.gtimg.com/qd/images/ico/default_user.0.2.png",
        "segmentId": 5,
        "content": "有人争辩那就成聊斋了",
        "status": 1,
        "createTime": "2023-04-03 00:04:01",
        "createTimestamp": 1680451441,
        "updateTime": "2024-07-05 21:58:34",
        "quoteReviewId": "849256195201761280",
        "quoteContent": "",
        "quoteGuid": "2136173392",
        "quoteUserId": "354168061",
        "quoteNickName": "桂曦月",
        "type": 10,
        "likeCount": 1,
        "dislikeCount": 0,
        "userLike": false,
        "userDislike": false,
        "isSelf": false,
        "essenceStatus": false,
        "riseStatus": false,
        "level": 803,
        "imagePre": "",
        "imageDetail": "",
        "rootReviewId": "849256195201761280",
        "rootReviewReplyCount": 0,
        "ipAddress": "广东"
      },
      {
        "reviewId": "850450193161388032",
        "cbid": "25583693309808304",
        "ccid": "69203747871449297",
        "guid": "120106156353",
        "userId": "335700445",
        "nickName": "几招散手",
        "avatar": "https://qidian.gtimg.com/qd/images/ico/default_user.0.2.png",
        "segmentId": 5,
        "content": "吻他，让他闭嘴",
        "status": 1,
        "createTime": "2023-03-07 19:41:42",
        "createTimestamp": 1678189302,
        "updateTime": "2024-07-05 21:58:34",
        "quoteReviewId": "849256763659976704",
        "quoteContent": "",
        "quoteGuid": "854040085984",
        "quoteUserId": "376427546",
        "quoteNickName": "铁尾铜鱼",
        "type": 10,
        "likeCount": 3,
        "dislikeCount": 0,
        "userLike": false,
        "userDislike": false,
        "isSelf": false,
        "essenceStatus": false,
        "riseStatus": false,
        "level": 779,
        "imagePre": "",
        "imageDetail": "",
        "rootReviewId": "849256195201761280",
        "rootReviewReplyCount": 0,
        "ipAddress": "甘肃"
      },
      {
        "reviewId": "850359599852552192",
        "cbid": "25583693309808304",
        "ccid": "69203747871449297",
        "guid": "800191074060",
        "userId": "191074060",
        "nickName": "fangblade",
        "avatar": "https://qidian.qpic.cn/qd_face/349573/8352386/100",
        "segmentId": 5,
        "content": "带点黑驴蹄子，饿了啃一口，有饥饿的人也可以给他啃一口",
        "status": 1,
        "createTime": "2023-03-07 13:41:43",
        "createTimestamp": 1678167703,
        "updateTime": "2024-07-05 21:58:34",
        "quoteReviewId": "849256195201761280",
        "quoteContent": "",
        "quoteGuid": "2136173392",
        "quoteUserId": "354168061",
        "quoteNickName": "桂曦月",
        "type": 10,
        "likeCount": 2,
        "dislikeCount": 0,
        "userLike": false,
        "userDislike": false,
        "isSelf": false,
        "essenceStatus": false,
        "riseStatus": false,
        "level": 778,
        "imagePre": "",
        "imageDetail": "",
        "rootReviewId": "849256195201761280",
        "rootReviewReplyCount": 0,
        "ipAddress": "黑龙江"
      },
      {
        "reviewId": "849828768406896640",
        "cbid": "25583693309808304",
        "ccid": "69203747871449297",
        "guid": "597468835",
        "userId": "222988911",
        "nickName": "开心庄园",
        "avatar": "https://qidian.qpic.cn/qd_face/349573/7235842/100",
        "segmentId": 5,
        "content": "尸体在说话",
        "status": 1,
        "createTime": "2023-03-06 02:32:23",
        "createTimestamp": 1678041143,
        "updateTime": "2024-07-05 21:58:34",
        "quoteReviewId": "849256195201761280",
        "quoteContent": "",
        "quoteGuid": "2136173392",
        "quoteUserId": "354168061",
        "quoteNickName": "桂曦月",
        "type": 10,
        "likeCount": 0,
        "dislikeCount": 0,
        "userLike": false,
        "userDislike": false,
        "isSelf": false,
        "essenceStatus": false,
        "riseStatus": false,
        "level": 768,
        "imagePre": "",
        "imageDetail": "",
        "rootReviewId": "849256195201761280",
        "rootReviewReplyCount": 0,
        "ipAddress": "福建"
      },
      {
        "reviewId": "849654657860829184",
        "cbid": "25583693309808304",
        "ccid": "69203747871449297",
        "guid": "854034896414",
        "userId": "375227607",
        "nickName": "枯桑知天风",
        "avatar": "https://qidian.qpic.cn/qd_face/349573/10643259/100",
        "segmentId": 5,
        "content": "马里奇：你礼貌吗？",
        "status": 1,
        "createTime": "2023-03-05 15:00:32",
        "createTimestamp": 1677999632,
        "updateTime": "2024-07-05 21:58:34",
        "quoteReviewId": "849276314963476480",
        "quoteContent": "",
        "quoteGuid": "854063165174",
        "quoteUserId": "406869520",
        "quoteNickName": "书友20230126175325999",
        "type": 10,
        "likeCount": 2,
        "dislikeCount": 0,
        "userLike": false,
        "userDislike": false,
        "isSelf": false,
        "essenceStatus": false,
        "riseStatus": false,
        "level": 757,
        "imagePre": "",
        "imageDetail": "",
        "rootReviewId": "849256195201761280",
        "rootReviewReplyCount": 0,
        "ipAddress": "湖北"
      },
      {
        "reviewId": "849621671626997760",
        "cbid": "25583693309808304",
        "ccid": "69203747871449297",
        "guid": "900010258952",
        "userId": "385672994",
        "nickName": "小小之恒",
        "avatar": "https://qidian.qpic.cn/qd_face/349573/10759278/100",
        "segmentId": 5,
        "content": "666",
        "status": 1,
        "createTime": "2023-03-05 12:49:28",
        "createTimestamp": 1677991768,
        "updateTime": "2024-07-05 21:58:34",
        "quoteReviewId": "849256195201761280",
        "quoteContent": "",
        "quoteGuid": "2136173392",
        "quoteUserId": "354168061",
        "quoteNickName": "桂曦月",
        "type": 10,
        "likeCount": 0,
        "dislikeCount": 0,
        "userLike": false,
        "userDislike": false,
        "isSelf": false,
        "essenceStatus": false,
        "riseStatus": false,
        "level": 750,
        "imagePre": "",
        "imageDetail": "",
        "rootReviewId": "849256195201761280",
        "rootReviewReplyCount": 0,
        "ipAddress": "江苏"
      },
      {
        "reviewId": "849614512944185344",
        "cbid": "25583693309808304",
        "ccid": "69203747871449297",
        "guid": "527095298",
        "userId": "215753885",
        "nickName": "鄙人名叫书小声",
        "avatar": "https://qidian.qpic.cn/qd_face/349573/7165930/100",
        "segmentId": 5,
        "content": "错啦，说不定都是活尸呢",
        "status": 1,
        "createTime": "2023-03-05 12:21:01",
        "createTimestamp": 1677990061,
        "updateTime": "2024-07-05 21:58:34",
        "quoteReviewId": "849256195201761280",
        "quoteContent": "",
        "quoteGuid": "2136173392",
        "quoteUserId": "354168061",
        "quoteNickName": "桂曦月",
        "type": 10,
        "likeCount": 2,
        "dislikeCount": 0,
        "userLike": false,
        "userDislike": false,
        "isSelf": false,
        "essenceStatus": false,
        "riseStatus": false,
        "level": 746,
        "imagePre": "",
        "imageDetail": "",
        "rootReviewId": "849256195201761280",
        "rootReviewReplyCount": 0,
        "ipAddress": "广东"
      },
      {
        "reviewId": "849564387248963584",
        "cbid": "25583693309808304",
        "ccid": "69203747871449297",
        "guid": "854002243517",
        "userId": "300158336",
        "nickName": "试试水0416",
        "avatar": "https://qidian.qpic.cn/qd_face/349573/267/100",
        "segmentId": 5,
        "content": "这话在这个诡异的世界可不敢说啊！[fn=16]",
        "status": 1,
        "createTime": "2023-03-05 09:01:50",
        "createTimestamp": 1677978110,
        "updateTime": "2024-07-05 21:58:33",
        "quoteReviewId": "849256195201761280",
        "quoteContent": "",
        "quoteGuid": "2136173392",
        "quoteUserId": "354168061",
        "quoteNickName": "桂曦月",
        "type": 10,
        "likeCount": 3,
        "dislikeCount": 0,
        "userLike": false,
        "userDislike": false,
        "isSelf": false,
        "essenceStatus": false,
        "riseStatus": false,
        "level": 723,
        "imagePre": "",
        "imageDetail": "",
        "rootReviewId": "849256195201761280",
        "rootReviewReplyCount": 0,
        "ipAddress": "江苏"
      },
      {
        "reviewId": "849451001626558464",
        "cbid": "25583693309808304",
        "ccid": "69203747871449297",
        "guid": "854046154143",
        "userId": "382882770",
        "nickName": "矿泉水花生瓜子小板凳",
        "avatar": "https://qidian.gtimg.com/qd/images/ico/default_user.0.2.png",
        "segmentId": 5,
        "content": "那就弄\"死\"他",
        "status": 1,
        "createTime": "2023-03-05 01:31:17",
        "createTimestamp": 1677951077,
        "updateTime": "2024-07-05 21:58:33",
        "quoteReviewId": "849256763659976704",
        "quoteContent": "",
        "quoteGuid": "854040085984",
        "quoteUserId": "376427546",
        "quoteNickName": "铁尾铜鱼",
        "type": 10,
        "likeCount": 1,
        "dislikeCount": 0,
        "userLike": false,
        "userDislike": false,
        "isSelf": false,
        "essenceStatus": false,
        "riseStatus": false,
        "level": 702,
        "imagePre": "",
        "imageDetail": "",
        "rootReviewId": "849256195201761280",
        "rootReviewReplyCount": 0,
        "ipAddress": "广西"
      }
    ],
    "total": 53,
    "isEnd": 0
  }
}
